.gitignore
LICENSE
MANIFEST.in
README.md
requirements.txt
setup.py
bin/update_pages.py
pyscp/__init__.py
pyscp/core.py
pyscp/orm.py
pyscp/snapshot.py
pyscp/utils.py
pyscp/wikidot.py
pyscp.egg-info/PKG-INFO
pyscp.egg-info/SOURCES.txt
pyscp.egg-info/dependency_links.txt
pyscp.egg-info/requires.txt
pyscp.egg-info/top_level.txt
pyscp/resources/cover.png
pyscp/resources/stafflist.txt
pyscp/resources/stylesheet.css
pyscp/resources/pages/cover.xhtml
pyscp/resources/pages/intro.xhtml
pyscp/resources/pages/license.xhtml
pyscp/resources/pages/title.xhtml
pyscp/resources/templates/container.xml
pyscp/resources/templates/content.opf
pyscp/resources/templates/page.xhtml
pyscp/resources/templates/toc.ncx
pyscp/stats/__init__.py
pyscp/stats/counters.py
pyscp/stats/filters.py
pyscp/stats/scalars.py
pyscp/stats/updater.py
tests/test_core.py