Metadata-Version: 2.1
Name: pyscp
Version: 1.1.19
Summary: Python API and utilities for the www.scpwiki.com website.
Home-page: https://github.com/MrNereof/pyscp/
Author: MrNereof
Author-email: mrnereof@gmail.com
License: MIT
Keywords: scp,wikidot
Platform: UNKNOWN
Classifier: Development Status :: 4 - Beta
Classifier: Intended Audience :: Other Audience
Classifier: License :: OSI Approved :: MIT License
Classifier: Operating System :: OS Independent
Classifier: Programming Language :: Python :: 3.4
Classifier: Programming Language :: Python :: 3.6
Classifier: Programming Language :: Python :: 3.7
Classifier: Programming Language :: Python :: 3.8
Classifier: Programming Language :: Python :: 3.9
Requires-Python: >=3.4
